milkycow/__init__.py
milkycow/decrypt.py
milkycow/encrypt.py
milkycow-0.0.5.dist-info/LICENSE
milkycow-0.0.5.dist-info/METADATA
milkycow-0.0.5.dist-info/WHEEL
milkycow-0.0.5.dist-info/top_level.txt
milkycow-0.0.5.dist-info/RECORD
