Metadata-Version: 2.1
Name: milkycow
Version: 0.0.5
Summary: Simple encryption
Home-page: https://github.com/Madhava-mng/Milkycow
Author: Madhava-mng
Author-email: alformint@gmail.com
License: UNKNOWN
Platform: UNKNOWN
Classifier: Programming Language :: Python :: 3
Classifier: License :: OSI Approved :: MIT License
Classifier: Operating System :: OS Independent
Requires-Python: >=3.6
